forgeimportmap/__init__.py
forgeimportmap/cli.py
forgeimportmap/core.py
forgeimportmap/generator.py
forgeimportmap/templates/importmap/scripts.html
forgeimportmap/templatetags/__init__.py
forgeimportmap/templatetags/importmap.py
forge_importmap-1.0.0.dist-info/METADATA
forge_importmap-1.0.0.dist-info/entry_points.txt
forge_importmap-1.0.0.dist-info/WHEEL
forge_importmap-1.0.0.dist-info/LICENSE
forge_importmap-1.0.0.dist-info/RECORD
