Metadata-Version: 2.1
Name: forge-importmap
Version: 1.0.0
Summary: JavaScript import maps for Django
Home-page: https://github.com/forgepackages/forge-importmap
License: MIT
Keywords: django,javascript,import,map,import-maps
Author: Dave Gaeddert
Author-email: dave.gaeddert@dropseed.dev
Requires-Python: >=3.8,<4.0
Classifier: Environment :: Web Environment
Classifier: Framework :: Django
Classifier: Intended Audience :: Developers
Classifier: License :: OSI Approved :: MIT License
Classifier: Operating System :: OS Independent
Classifier: Programming Language :: Python
Classifier: Programming Language :: Python :: 3
Classifier: Programming Language :: Python :: 3.8
Classifier: Programming Language :: Python :: 3.9
Classifier: Programming Language :: Python :: 3.10
Classifier: Programming Language :: Python :: 3.11
Classifier: Programming Language :: Python :: 3
Classifier: Programming Language :: Python :: 3 :: Only
Classifier: Programming Language :: Python :: 3.10
Classifier: Programming Language :: Python :: 3.8
Classifier: Programming Language :: Python :: 3.9
Requires-Dist: click
Requires-Dist: forge-core (>=1.0.0,<2.0.0)
Requires-Dist: marshmallow (>=3.14.1,<4.0.0)
Requires-Dist: requests
Requires-Dist: tomli
Project-URL: Documentation, https://github.com/forgepackages/forge-importmap
Project-URL: Repository, https://github.com/forgepackages/forge-importmap
